<?xml version="1.0" encoding="utf-8"?>
<!DOCTYPE hibernate-mapping PUBLIC "-//Hibernate/Hibernate Mapping DTD 3.0//EN"
"http://hibernate.sourceforge.net/hibernate-mapping-3.0.dtd">
<!-- 
    Mapping file autogenerated by MyEclipse Persistence Tools
-->
<hibernate-mapping package="com.chinasoft.domain">
    <class name="Student" table="testStudent" schema="user_zhouqi">
		<composite-id class="StudentId" name="id">
			<key-property name="fristName" column="frist1" length="20"></key-property>
			<key-property name="lastName" column="last1" length="30"></key-property>
		</composite-id>
  		<property name="age">  		
  		
  		</property>
  		
    </class>
</hibernate-mapping>
